{
  "version": "1.0",
  "lastUpdated": "2024-06-17",
  "files": {
    "talent_attraction_2024": {
      "fileId": "talent_attraction_2024",
      "topicId": "Attraction_Factors",
      "year": 2024,
      "isComparable": false,
      "reason": "Methodology changed between 2024 and 2025"
    },
    "talent_retention_2024": {
      "fileId": "talent_retention_2024",
      "topicId": "Retention_Factors",
      "year": 2024,
      "isComparable": false,
      "reason": "Question format changed between years"
    },
    "talent_attrition_2024": {
      "fileId": "talent_attrition_2024",
      "topicId": "Attrition_Factors",
      "year": 2024,
      "isComparable": false,
      "reason": "Response scales changed between 2024 and 2025"
    },
    "talent_attraction_2025": {
      "fileId": "talent_attraction_2025",
      "topicId": "Attraction_Factors",
      "year": 2025,
      "isComparable": false,
      "reason": "Methodology changed between 2024 and 2025"
    },
    "talent_retention_2025": {
      "fileId": "talent_retention_2025",
      "topicId": "Retention_Factors",
      "year": 2025,
      "isComparable": false,
      "reason": "Question format changed between years"
    },
    "talent_attrition_2025": {
      "fileId": "talent_attrition_2025",
      "topicId": "Attrition_Factors",
      "year": 2025,
      "isComparable": false,
      "reason": "Response scales changed between 2024 and 2025"
    }
  },
  "topics": {
    "Attraction_Factors": {
      "topicId": "Attraction_Factors",
      "parentTheme": "Talent Attraction & Retention",
      "isComparable": false,
      "userMessage": "Year-on-year comparisons are not available for attraction factors due to methodology changes between 2024 and 2025.",
      "canonicalQuestion": "What factors attract candidates to our organization?",
      "years": [2024, 2025]
    },
    "Retention_Factors": {
      "topicId": "Retention_Factors",
      "parentTheme": "Talent Attraction & Retention",
      "isComparable": false,
      "userMessage": "Year-on-year comparisons are not available for retention factors due to changes in question format between years.",
      "canonicalQuestion": "What factors contribute to employee retention?",
      "years": [2024, 2025]
    },
    "Attrition_Factors": {
      "topicId": "Attrition_Factors",
      "parentTheme": "Talent Attraction & Retention",
      "isComparable": false,
      "userMessage": "Year-on-year comparisons are not available for attrition factors due to changes in response scales between 2024 and 2025.",
      "canonicalQuestion": "What factors lead to employee attrition?",
      "years": [2024, 2025]
    }
  }
} 